{"name":"Java-kata","tagline":"playground for katas","body":"JAVA-KATA\r\n=========\r\n[![Build Status](https://secure.travis-ci.org/kpacha/java-kata.png?branch=master)](https://travis-ci.org/kpacha/java-kata)\r\n\r\nA collection of (easy) katas in java\r\n\r\n###Prime Numbers\r\n\r\n(from http://butunclebob.com/ArticleS.UncleBob.ThePrimeFactorsKata)\r\n\r\nDecompose any number in its prime factors\r\n\r\n###FizzBuzz\r\n\r\n(from http://codingdojo.org/cgi-bin/wiki.pl?KataFizzBuzz)\r\n\r\nA simple FizzBuzz implementation\r\n\r\n###Roman Numerals\r\n\r\n(from http://codingdojo.org/cgi-bin/wiki.pl?KataRomanNumerals)\r\n\r\nA simple number converter - from Roman to Arabic and reverse.\r\n\r\n###Potter Kata\r\n\r\n(from http://codingdojo.org/cgi-bin/wiki.pl?KataPotter)\r\n\r\nA simple discount calculator.\r\n\r\n###Anagram Kata\r\n\r\nWrite a program to generate all potential anagrams of an input string.\r\nFor example, the potential anagrams of abcd are\r\n\r\n    abcd, abdc, acbd, acdb, adbc, adcb,\r\n    bacd, badc, bcad, bcda, bdac, bdca,\r\n    cabd, cadb, cbad, cbda, cdab, cdba,\r\n    dabc, dacb, dbac, dbca, dcab, dcba\r\n\r\n###Tennis Kata\r\n\r\n(from http://codingdojo.org/cgi-bin/wiki.pl?KataTennis)\r\n\r\nA tennis score calculator. The scoring system is rather simple:\r\n\r\n* Each player can have either of these points in one game 0 15 30 40\r\n* If you have 40 and you win the ball you win the game, however there are special rules.\r\n* If both have 40 the players are deuce.\r\n* If the game is in deuce, the winner of a ball will have advantage and game ball.\r\n* If the player with advantage wins the ball he wins the game\r\n* If the player without advantage wins they are back at deuce.\r\n\r\n###PokerHands Kata\r\n\r\n(from http://codingdojo.org/cgi-bin/wiki.pl?KataPokerHands)\r\n\r\nCompare several pairs of poker hands and indicate which, if either, has a higher rank.\r\n\r\n\r\n\r\n\r\n[![Bitdeli Badge](https://d2weczhvl823v0.cloudfront.net/kpacha/java-kata/trend.png)](https://bitdeli.com/free \"Bitdeli Badge\")\r\n\r\n","google":"","note":"Don't delete this file! It's used internally to help with page regeneration."}